myprofiler/__init__.py
myprofiler-0.0.1.dist-info/LICENSE
myprofiler-0.0.1.dist-info/METADATA
myprofiler-0.0.1.dist-info/WHEEL
myprofiler-0.0.1.dist-info/top_level.txt
myprofiler-0.0.1.dist-info/RECORD
