Metadata-Version: 2.1
Name: myprofiler
Version: 0.0.1
Summary: A minimal profiler for calculating memory usage and time
Author-email: AmirBahador Bahadori <amirbahador.pv@gmail.com>
License: MIT License
Project-URL: repository, https://github.com/amirbahador-hub/myprofiler
Keywords: profiler,memory usage,python performance
Classifier: License :: OSI Approved :: Apache Software License
Classifier: Programming Language :: Python
Classifier: Programming Language :: Python :: 3
Requires-Python: >=3.10
License-File: LICENSE
Provides-Extra: build
Requires-Dist: build ; extra == 'build'
Requires-Dist: twine ; extra == 'build'
Requires-Dist: bumpver ; extra == 'build'
